LICENSE
MANIFEST.in
README.md
setup.py
django_ldap3_sync.egg-info/PKG-INFO
django_ldap3_sync.egg-info/SOURCES.txt
django_ldap3_sync.egg-info/dependency_links.txt
django_ldap3_sync.egg-info/requires.txt
django_ldap3_sync.egg-info/top_level.txt
docs/changelog.md
ldap3_sync/__init__.py
ldap3_sync/admin.py
ldap3_sync/apps.py
ldap3_sync/models.py
ldap3_sync/runtests.py
ldap3_sync/tasks.py
ldap3_sync/utils.py
ldap3_sync/management/__init__.py
ldap3_sync/management/commands/__init__.py
ldap3_sync/management/commands/syncldap.py