Metadata-Version: 1.1
Name: django-ldap3-sync
Version: 1.0.1
Summary: A Django application for synchronizing LDAP objects to Django models.
Home-page: https://github.com/PGower/django-ldap3-sync
Author: Paul Gower
Author-email: p.gower@gmail.com
License: MIT
Download-URL: https://github.com/PGower/django-ldap3-sync/releases
Keywords: django,ldap,active directory,synchronize,sync
Platform: UNKNOWN
Classifier: Development Status :: 3 - Alpha
Classifier: Environment :: Web Environment
Classifier: Programming Language :: Python
Classifier: Framework :: Django
Classifier: Intended Audience :: Developers
Classifier: License :: OSI Approved :: BSD License
Classifier: Operating System :: OS Independent
Classifier: Topic :: System :: Systems Administration :: Authentication/Directory
Classifier: Topic :: Software Development :: Libraries :: Python Modules
